[{"title":"韩国女装","imgsrc":"imgs/1.jpg","author":"888"},
{"title":"韩国女装","imgsrc":"imgs/732779_16731271_k3.gif","author":"888"},
{"title":"韩国女装","imgsrc":"imgs/783886_17111565_k3.gif","author":"888"},
{"title":"韩国女装","imgsrc":"imgs/809559_17193088_k3.gif","author":"888"},
{"title":"韩国女装","imgsrc":"imgs/784437_17111539_k3.gif","author":"888"},
{"title":"韩国女装","imgsrc":"imgs/810443_17220233_k3.gif","author":"888"},
{"title":"韩国女装","imgsrc":"imgs/810502_17220243_k3.gif","author":"888"},
{"title":"韩国女装","imgsrc":"imgs/809427_17193108_k3.gif","author":"888"},
{"title":"韩国女装","imgsrc":"imgs/808054_17189337_k3.gif","author":"888"},
{"title":"韩国女装","imgsrc":"imgs/808053_17189329_k3.jpg","author":"888"},
{"title":"韩国女装","imgsrc":"imgs/807606_17186963_k3.gif","author":"888"},
{"title":"韩国女装","imgsrc":"imgs/808063_17189403_k3.gif","author":"888"}]

